ovs_helper/__init__.py
ovs_helper/bridge.py
ovs_helper/db_client.py
ovs_helper/vsctl.py
ovs_helper/vswitch_idl.py
ovs_helper-0.0.5.dist-info/DESCRIPTION.rst
ovs_helper-0.0.5.dist-info/METADATA
ovs_helper-0.0.5.dist-info/RECORD
ovs_helper-0.0.5.dist-info/WHEEL
ovs_helper-0.0.5.dist-info/metadata.json
ovs_helper-0.0.5.dist-info/top_level.txt
