Metadata-Version: 2.0
Name: ovs-helper
Version: 0.0.5
Summary: Ovs-helper to Open vSwitch
Home-page: https://github.com/sw4iot/ovs-helper
Author: SOFTWAY4IoT
Author-email: softway4iot@gmail.com
License: Apache Software License
Keywords: ovs-helper
Platform: UNKNOWN
Classifier: Development Status :: 3 - Alpha
Classifier: License :: OSI Approved :: Apache Software License
Classifier: Intended Audience :: Developers
Classifier: Natural Language :: English
Classifier: Operating System :: OS Independent
Classifier: Programming Language :: Python :: 2.7
Classifier: Programming Language :: Python :: 3.4
Classifier: Programming Language :: Python :: 3.5
Requires-Dist: ryu (>=4.30)
